masonite/inertia/__init__.py
masonite/inertia/helpers.py
masonite/inertia/config/inertia.py
masonite/inertia/core/Inertia.py
masonite/inertia/core/InertiaResponse.py
masonite/inertia/core/Lazy.py
masonite/inertia/core/__init__.py
masonite/inertia/middleware/InertiaMiddleware.py
masonite/inertia/providers/InertiaProvider.py
masonite/inertia/providers/__init__.py
masonite/inertia/testing/InertiaTestingResponse.py
masonite/inertia/testing/__init__.py
masonite_inertia-4.2.4.dist-info/LICENSE
masonite_inertia-4.2.4.dist-info/METADATA
masonite_inertia-4.2.4.dist-info/WHEEL
masonite_inertia-4.2.4.dist-info/top_level.txt
masonite_inertia-4.2.4.dist-info/RECORD
